{
  "collectionName": "components_blocks_homepage_headers",
  "info": {
    "displayName": "Homepage Header",
    "icon": "archway",
    "description": ""
  },
  "options": {},
  "attributes": {
    "subtitle": {
      "type": "string"
    },
    "picture": {
      "type": "media",
      "multiple": false,
      "required": false,
      "allowedTypes": [
        "images",
        "files",
        "videos",
        "audios"
      ]
    },
    "mobilePicture": {
      "type": "media",
      "multiple": false,
      "required": false,
      "allowedTypes": [
        "images",
        "files",
        "videos",
        "audios"
      ]
    },
    "title": {
      "type": "string"
    }
  }
}
